oriole_service/__init__.py
oriole_service/api.py
oriole_service/app.py
oriole_service/cli.py
oriole_service/db.py
oriole_service/log.py
oriole_service/test.py
oriole_service/modules/__init__.py
oriole_service/modules/build.py
oriole_service/modules/conf.py
oriole_service/modules/doc.py
oriole_service/modules/halt.py
oriole_service/modules/i18n.py
oriole_service/modules/oc
oriole_service/modules/run.py
oriole_service/modules/sh.py
oriole_service/modules/test.py
oriole_service-30.8.0.data/data/bin/oc
oriole_service-30.8.0.dist-info/LICENSE
oriole_service-30.8.0.dist-info/METADATA
oriole_service-30.8.0.dist-info/WHEEL
oriole_service-30.8.0.dist-info/entry_points.txt
oriole_service-30.8.0.dist-info/top_level.txt
oriole_service-30.8.0.dist-info/zip-safe
oriole_service-30.8.0.dist-info/RECORD
