Metadata-Version: 2.1
Name: oriole-service
Version: 30.8.0
Summary: Rapidly create services.
Home-page: https://github.com/oriole-island/oriole-service
Author: Eric.Zhou
Author-email: xiaoxiang.cn@gmail.com
License: Apache License, Version 2.0
Platform: UNKNOWN
Classifier: Programming Language :: Python
Classifier: Operating System :: POSIX
Classifier: Programming Language :: Python :: 3
Classifier: Programming Language :: Python :: 3.6
Classifier: Topic :: Internet
Classifier: Topic :: Software Development :: Libraries :: Python Modules
Classifier: Intended Audience :: Developers
Requires-Dist: nameko (==2.12.0)
Requires-Dist: nameko-tracer (==1.2.0)
Requires-Dist: oriole (>=22.0.0)
